drf_firebase_auth/__init__.py
drf_firebase_auth/apps.py
drf_firebase_auth/authentication.py
drf_firebase_auth/models.py
drf_firebase_auth/settings.py
drf_firebase_auth/utils.py
drf_firebase_auth/migrations/0001_initial.py
drf_firebase_auth/migrations/__init__.py
drf_firebase_auth-1.0.0.dist-info/LICENSE
drf_firebase_auth-1.0.0.dist-info/METADATA
drf_firebase_auth-1.0.0.dist-info/WHEEL
drf_firebase_auth-1.0.0.dist-info/top_level.txt
drf_firebase_auth-1.0.0.dist-info/RECORD
