Metadata-Version: 2.1
Name: drf-firebase-auth
Version: 1.0.0
Summary: Custom Django Rest Framework authentication backend for parsing Firebase uid tokens and storing as local users.
Home-page: https://github.com/garyburgmann/drf-firebase-auth
Author: Gary Burgmann
Author-email: garyburgmann@gmail.com
License: MIT
Keywords: drf,django,rest_framework,djangorestframework,authentication,python3,firebase
Platform: UNKNOWN
Classifier: Environment :: Web Environment
Classifier: Framework :: Django
Classifier: Intended Audience :: Developers
Classifier: License :: OSI Approved :: MIT License
Classifier: Operating System :: OS Independent
Classifier: Programming Language :: Python :: 3
Classifier: Topic :: Internet :: WWW/HTTP
Requires-Python: >=3.4
Requires-Dist: djangorestframework (<4,>=3.9)
Requires-Dist: firebase-admin (<5,>=4.5)
